<?xml version="1.0" encoding="UTF-8"?>
<?xml-model href="../../../Schema/Schema1.rnc" type="application/relax-ng-compact-syntax"?>
<meme>
    <title>Distracted Boyfriend 11</title>
    <text type="floating">
        <frag n="1">
            <phrase role="SUBJ" pos="N">America's oil</phrase>
        </frag>
        <frag n="2">
            <phrase role="SUBJ" pos="N">America</phrase>
        </frag>
        <frag n="3">
            <phrase role="SUBJ" pos="N">Other countries oil</phrase>
        </frag>
    </text>
</meme>
